viperthon/basic.py
viperthon/dataframe.py
viperthon/viperthon.py
viperthon-1.0.1.dist-info/LICENSE
viperthon-1.0.1.dist-info/METADATA
viperthon-1.0.1.dist-info/WHEEL
viperthon-1.0.1.dist-info/top_level.txt
viperthon-1.0.1.dist-info/RECORD
