Metadata-Version: 2.1
Name: viperthon
Version: 1.0.1
Summary: Tool to perform basic operations on your Dataset
Home-page: https://github.com/swatishayna/viperthon.git
Author: Swati Pandey
License: MIT
Platform: UNKNOWN
Classifier: Programming Language :: Python :: 3
Classifier: Programming Language :: Python :: 3.6
Classifier: License :: OSI Approved :: MIT License
Classifier: Operating System :: OS Independent
Requires-Python: >=3.6
Requires-Dist: pandas
